kwdagger/__init__.py
kwdagger/__main__.py
kwdagger/aggregate.py
kwdagger/aggregate_loader.py
kwdagger/aggregate_plots.py
kwdagger/pipeline.py
kwdagger/query_plan.py
kwdagger/result_parser.py
kwdagger/schedule.py
kwdagger/demo/__init__.py
kwdagger/demo/demodata.py
kwdagger/examples/__init__.py
kwdagger/mlops/__init__.py
kwdagger/mlops/__main__.py
kwdagger/mlops/aggregate.py
kwdagger/mlops/aggregate_loader.py
kwdagger/mlops/aggregate_plots.py
kwdagger/mlops/mlops_demodata.py
kwdagger/mlops/pipeline_nodes.py
kwdagger/mlops/query_plan.py
kwdagger/mlops/schedule_evaluation.py
kwdagger/mlops/smart_global_helper.py
kwdagger/mlops/smart_result_parser.py
kwdagger/utils/__init__.py
kwdagger/utils/result_analysis.py
kwdagger/utils/reverse_hashid.py
kwdagger/utils/util_dotdict.py
kwdagger/utils/util_kwplot.py
kwdagger/utils/util_nvidia.py
kwdagger/utils/util_pandas.py
kwdagger/utils/util_param_grid.py
kwdagger/utils/util_stringalgo.py
kwdagger/utils/util_tables.py
kwdagger-0.2.1.dist-info/METADATA
kwdagger-0.2.1.dist-info/WHEEL
kwdagger-0.2.1.dist-info/entry_points.txt
kwdagger-0.2.1.dist-info/top_level.txt
kwdagger-0.2.1.dist-info/RECORD
